xontrib/skim.py
xontrib_skim-0.0.6.dist-info/METADATA
xontrib_skim-0.0.6.dist-info/WHEEL
xontrib_skim-0.0.6.dist-info/RECORD
