Metadata-Version: 2.1
Name: xontrib-skim
Version: 0.0.6
Summary: skim (fuzzy finder) integration
Home-page: https://github.com/eugenesvk/xontrib-skim
License: MIT
Keywords: xontrib,xonsh
Author: Evgeny
Author-email: es.bugzilla@gmail.com
Requires-Python: >=3.9,<4.0
Classifier: Intended Audience :: Developers
Classifier: License :: OSI Approved :: MIT License
Classifier: Natural Language :: English
Classifier: Operating System :: OS Independent
Classifier: Programming Language :: Python :: 3
Classifier: Programming Language :: Python :: 3.9
Classifier: Programming Language :: Python :: 3.10
Classifier: Programming Language :: Python :: 3.11
Classifier: Programming Language :: Python :: 3.12
Classifier: Topic :: System :: Shells
Classifier: Topic :: System :: System Shells
Classifier: Topic :: Terminals
Requires-Dist: prompt-toolkit (>=3.0.47,<4.0.0)
Requires-Dist: xonsh (>=0.18.2)
Project-URL: Code, https://github.com/eugenesvk/xontrib-skim
Project-URL: Documentation, https://github.com/eugenesvk/xontrib-skim/blob/master/ReadMe.md
Project-URL: Issue tracker, https://github.com/eugenesvk/xontrib-skim/issues
Project-URL: Repository, https://github.com/eugenesvk/xontrib-skim
